docs/ucx/src/components/Button.tsx
docs/ucx/src/css/custom.css
docs/ucx/src/pages/index.tsx
databricks/__init__.py
databricks/labs/__init__.py
databricks/labs/ucx/__about__.py
databricks/labs/ucx/__init__.py
databricks/labs/ucx/cli.py
databricks/labs/ucx/config.py
databricks/labs/ucx/github.py
databricks/labs/ucx/install.py
databricks/labs/ucx/runtime.py
databricks/labs/ucx/uninstall.py
databricks/labs/ucx/account/__init__.py
databricks/labs/ucx/account/aggregate.py
databricks/labs/ucx/account/metastores.py
databricks/labs/ucx/account/workspaces.py
databricks/labs/ucx/assessment/__init__.py
databricks/labs/ucx/assessment/aws.py
databricks/labs/ucx/assessment/azure.py
databricks/labs/ucx/assessment/clusters.py
databricks/labs/ucx/assessment/crawlers.py
databricks/labs/ucx/assessment/dashboards.py
databricks/labs/ucx/assessment/export.py
databricks/labs/ucx/assessment/export_html_template.py
databricks/labs/ucx/assessment/init_scripts.py
databricks/labs/ucx/assessment/jobs.py
databricks/labs/ucx/assessment/pipelines.py
databricks/labs/ucx/assessment/secrets.py
databricks/labs/ucx/assessment/sequencing.py
databricks/labs/ucx/assessment/workflows.py
databricks/labs/ucx/aws/__init__.py
databricks/labs/ucx/aws/access.py
databricks/labs/ucx/aws/credentials.py
databricks/labs/ucx/aws/locations.py
databricks/labs/ucx/azure/__init__.py
databricks/labs/ucx/azure/access.py
databricks/labs/ucx/azure/credentials.py
databricks/labs/ucx/azure/locations.py
databricks/labs/ucx/azure/resources.py
databricks/labs/ucx/contexts/__init__.py
databricks/labs/ucx/contexts/account_cli.py
databricks/labs/ucx/contexts/application.py
databricks/labs/ucx/contexts/workflow_task.py
databricks/labs/ucx/contexts/workspace_cli.py
databricks/labs/ucx/framework/__init__.py
databricks/labs/ucx/framework/crawlers.py
databricks/labs/ucx/framework/owners.py
databricks/labs/ucx/framework/tasks.py
databricks/labs/ucx/framework/utils.py
databricks/labs/ucx/hive_metastore/__init__.py
databricks_labs_ucx-0.60.1.dist-info/METADATA
databricks_labs_ucx-0.60.1.dist-info/WHEEL
databricks_labs_ucx-0.60.1.dist-info/entry_points.txt
databricks_labs_ucx-0.60.1.dist-info/licenses/LICENSE
databricks_labs_ucx-0.60.1.dist-info/licenses/NOTICE
databricks_labs_ucx-0.60.1.dist-info/RECORD
