Metadata-Version: 2.4
Name: databricks-labs-ucx
Version: 0.60.1
Summary: UCX - Unity Catalog Migration Toolkit
Project-URL: Issues, https://github.com/databricks/ucx/issues
Project-URL: Source, https://github.com/databricks/ucx
Author-email: Serge Smertin <serge.smertin@databricks.com>
Maintainer-email: Serge Smertin <serge.smertin@databricks.com>, Liran Bareket <liran.bareket@databricks.com>, Marcin Wojtyczka <marcin.wojtyczka@databricks.com>, Ziyuan Qin <ziyuan.qin@databricks.com>, William Conti <william.conti@databricks.com>, Hari Selvarajan <hari.selvarajan@databricks.com>, Vuong Nguyen <vuong.nguyen@databricks.com>
License-File: LICENSE
License-File: NOTICE
Keywords: Databricks,Unity Catalog
Classifier: Development Status :: 4 - Beta
Classifier: Environment :: Console
Classifier: Framework :: Pytest
Classifier: Intended Audience :: Developers
Classifier: Intended Audience :: System Administrators
Classifier: License :: Other/Proprietary License
Classifier: Operating System :: MacOS
Classifier: Operating System :: Microsoft :: Windows
Classifier: Programming Language :: Python
Classifier: Programming Language :: Python :: 3.10
Classifier: Programming Language :: Python :: 3.11
Classifier: Programming Language :: Python :: 3.12
Classifier: Programming Language :: Python :: Implementation :: CPython
Classifier: Topic :: Software Development :: Libraries
Classifier: Topic :: Utilities
Requires-Python: >=3.10
Requires-Dist: astroid<3.4.0,>=3.3.0
Requires-Dist: databricks-labs-blueprint<0.12.0,>=0.11.0
Requires-Dist: databricks-labs-lsql<0.17.0,>=0.16.0
Requires-Dist: databricks-sdk<0.59.0,>=0.58.0
Requires-Dist: pyyaml<6.1.0,>=6.0.0
Requires-Dist: sqlglot<27.1.0,>=26.7.0
Provides-Extra: pylsp
Requires-Dist: python-lsp-server<1.14.0,>=1.13.0; extra == 'pylsp'
